docs/__init__.py
docs/routes.py
docs/static/assets/css/globals.css
docs/static/assets/images/screen-shot-narrow.png
docs/static/assets/images/screen-shot-wide.png
docs/static/assets/svgs/logo.svg
docs/static/pwa/android/android-launchericon-144-144.png
docs/static/pwa/android/android-launchericon-192-192.png
docs/static/pwa/android/android-launchericon-48-48.png
docs/static/pwa/android/android-launchericon-512-512.png
docs/static/pwa/android/android-launchericon-72-72.png
docs/static/pwa/android/android-launchericon-96-96.png
docs/static/pwa/favicon.ico
docs/static/pwa/ios/100.png
docs/static/pwa/ios/1024.png
docs/static/pwa/ios/114.png
docs/static/pwa/ios/120.png
docs/static/pwa/ios/128.png
docs/static/pwa/ios/144.png
docs/static/pwa/ios/152.png
docs/static/pwa/ios/16.png
docs/static/pwa/ios/167.png
docs/static/pwa/ios/180.png
docs/static/pwa/ios/192.png
docs/static/pwa/ios/20.png
docs/static/pwa/ios/256.png
docs/static/pwa/ios/29.png
docs/static/pwa/ios/32.png
docs/static/pwa/ios/40.png
docs/static/pwa/ios/50.png
docs/static/pwa/ios/512.png
docs/static/pwa/ios/57.png
docs/static/pwa/ios/58.png
docs/static/pwa/ios/60.png
docs/static/pwa/ios/64.png
docs/static/pwa/ios/72.png
docs/static/pwa/ios/76.png
docs/static/pwa/ios/80.png
docs/static/pwa/ios/87.png
docs/static/pwa/manifest.json
docs/static/pwa/opengraph-image.png
docs/static/pwa/robots.txt
docs/static/pwa/windows11/LargeTile.scale-100.png
docs/static/pwa/windows11/LargeTile.scale-125.png
docs/static/pwa/windows11/LargeTile.scale-150.png
docs/static/pwa/windows11/LargeTile.scale-200.png
docs/static/pwa/windows11/LargeTile.scale-400.png
docs/static/pwa/windows11/SmallTile.scale-100.png
docs/static/pwa/windows11/SmallTile.scale-125.png
docs/static/pwa/windows11/SmallTile.scale-150.png
docs/static/pwa/windows11/SmallTile.scale-200.png
docs/static/pwa/windows11/SmallTile.scale-400.png
docs/static/pwa/windows11/SplashScreen.scale-100.png
docs/static/pwa/windows11/SplashScreen.scale-125.png
pg_fms-0.2.1.dist-info/METADATA
pg_fms-0.2.1.dist-info/WHEEL
pg_fms-0.2.1.dist-info/entry_points.txt
pg_fms-0.2.1.dist-info/licenses/LICENSE
pg_fms-0.2.1.dist-info/RECORD
