Metadata-Version: 2.1
Name: pg-fms
Version: 0.2.1
Summary: The Purple Geckos File Management System (PG-FMS) is an advanced, Python-based file management solution designed to streamline and enhance file handling tasks.
Author-Email: Mike Odnis <airwolf635@gmail.com>, Pankti Mehta <pnm1@rice.edu>, Vay Manning <jmanning7@dmacc.edu>
License: MIT
Project-URL: Source, https://gitlab.com/WomB0ComB0/pg-fms
Requires-Python: >=3.12
Requires-Dist: click
